psi_io/__init__.py
psi_io/data.py
psi_io/psi_io.py
psi_io-2.0.4.dist-info/licenses/LICENSE.txt
psi_io-2.0.4.dist-info/METADATA
psi_io-2.0.4.dist-info/WHEEL
psi_io-2.0.4.dist-info/top_level.txt
psi_io-2.0.4.dist-info/RECORD
